{
  "$schema": "https://hypar.io/Schemas/Function.json",
  "id": "2586d6e9-8586-42a0-9d49-b80d0d684925",
  "name": "Lounge Layout",
  "description": "Layout lounge spaces",
  "model_output": "Lounge Layout",
  "language": "C#",
  "model_dependencies": [
    {
      "autohide": false,
      "name": "Space Planning Zones",
      "optional": false
    },
    {
      "autohide": false,
      "name": "Circulation",
      "optional": true
    },
    {
      "autohide": false,
      "name": "Levels",
      "optional": true
    },
    {
      "autohide": false,
      "name": "Conceptual Mass",
      "optional": true
    }
  ],
  "overrides": {
    "Furniture Locations": {
      "perParent": "Level",
      "context": "[*discriminator=Elements.ElementInstance]",
      "identity": {
        "OriginalLocation": {
          "$ref": "https://schemas.hypar.io/Vector3.json"
        },
        "gltfLocation": {
          "type": "string"
        }
      },
      "schema": {
        "Transform": {
          "$ref": "https://schemas.hypar.io/Transform.json"
        }
      }
    }
  },
  "element_types": [
    "https://schemas.hypar.io/SpaceBoundary.json",
    "https://schemas.hypar.io/LevelElements.json",
    "https://schemas.hypar.io/CirculationSegment.json",
    "https://schemas.hypar.io/LevelVolume.json"
  ],
  "repository_url": "https://github.com/hypar-io/function",
  "source_file_key": null,
  "preview_image": null
}